LICENSE
MANIFEST.in
README.md
requirements.txt
setup.py
antlr_tsql/__init__.py
antlr_tsql/ast.py
antlr_tsql.egg-info/PKG-INFO
antlr_tsql.egg-info/SOURCES.txt
antlr_tsql.egg-info/dependency_links.txt
antlr_tsql.egg-info/requires.txt
antlr_tsql.egg-info/top_level.txt
antlr_tsql/antlr_py/__init__.py
antlr_tsql/antlr_py/tsql.interp
antlr_tsql/antlr_py/tsql.tokens
antlr_tsql/antlr_py/tsqlLexer.interp
antlr_tsql/antlr_py/tsqlLexer.py
antlr_tsql/antlr_py/tsqlLexer.tokens
antlr_tsql/antlr_py/tsqlListener.py
antlr_tsql/antlr_py/tsqlParser.py
antlr_tsql/antlr_py/tsqlVisitor.py