Metadata-Version: 2.1
Name: antlr-tsql
Version: 0.12.3
Summary: A transact sql parser, written in Antlr4
Home-page: https://github.com/datacamp/antlr-tsql
Author: Michael Chow
Author-email: michael@datacamp.com
Maintainer: Jeroen Hermans
Maintainer-email: content-engineering@datacamp.com
License: UNKNOWN
Platform: UNKNOWN
Classifier: Programming Language :: Python :: 3
Classifier: License :: OSI Approved :: GNU Affero General Public License v3
Classifier: Operating System :: OS Independent
